<?xml version="1.0" encoding="UTF-8" standalone="yes"?>
<userCollection>
    <user>
        <name>Juan</name>
        <mail>juan@gmail.com</mail>
        <password>03ac674216f3e15c761ee1a5e255f067953623c8b388b4459e13f978d7c846f4</password>
    </user>
    <user>
        <name>Pedro</name>
        <mail>pedro@gmail.com</mail>
        <password>03ac674216f3e15c761ee1a5e255f067953623c8b388b4459e13f978d7c846f4</password>
    </user>
    <user>
        <name>Antonio Guerola Crespo</name>
        <mail>antonioguerola@gmail.com</mail>
        <password>03ac674216f3e15c761ee1a5e255f067953623c8b388b4459e13f978d7c846f4</password>
    </user>
</userCollection>
